{
  "sections": {
    "79e8d093-77c2-4588-8678-9f011397b349": {
      "type": "slideshow",
      "blocks": {
        "template--16816867967201__79e8d093-77c2-4588-8678-9f011397b349-hero-1": {
          "type": "hero",
          "settings": {
            "top_subheading": "",
            "title": "<h1>Redefine Group Meetings with Our 6 Person Office Pod<\/h1>",
            "title_size": 59,
            "subheading": "Are you in search of a meeting space that fosters teamwork, creativity, and productivity on a larger scale? Look no further. Our Quell 6-person office pod is designed to provide a spacious and acoustically superior environment for your team meetings, brain storming sessions, and collaborative projects.",
            "link": "",
            "link_text": "",
            "link_2": "",
            "link_text_2": "",
            "color_accent": "#ffffff",
            "text_align": "vertical-center horizontal-left",
            "image": "shopify:\/\/shop_images\/L_White-Banner-main_1d4268c0-7e2c-43be-b4b5-9df08af8141e.png",
            "image_mobile": "shopify:\/\/shop_images\/L_White-Banner-main_Mob.png",
            "overlay_opacity": 26,
            "focal_point": "center center"
          }
        }
      },
      "block_order": [
        "template--16816867967201__79e8d093-77c2-4588-8678-9f011397b349-hero-1"
      ],
      "custom_css": [
        ".index-section {padding: 0; margin: 0;}"
      ],
      "settings": {
        "full_width": true,
        "desktop_size": 0,
        "mobile_size": 0,
        "style": "minimal",
        "arrow_slide": false,
        "autoplay": false,
        "autoplay_speed": 5,
        "section_class": ""
      }
    },
    "main-collection": {
      "type": "main-collection-next",
      "blocks": {
        "ecfa648a-5738-4acd-a6f1-fe8b501e3872": {
          "type": "product",
          "settings": {
            "product": "meeting-booth-4-6-persons-old",
            "image": "shopify:\/\/shop_images\/XLarge_White_DarkGreyInterior_Set1_01_856a9f98-fbec-4626-9788-44e1b832aa75.png",
            "image_bg": "shopify:\/\/shop_images\/sbs-stn6-3-4-bg.jpg",
            "title": "Quell- Meeting Booth - 6 Person",
            "content": "<p>Discover the Power of Our Spacious 6 Person Meeting Pod<\/p><p>At Soundbox Store, we understand the evolving needs of modern workplaces. Our Quell 6-person meeting pod is the epitome of spaciousness and acoustic excellence, tailored to optimise your office<br\/>environment.<\/p>",
            "url": "\/products\/meeting-booth-4-6-persons?variant=42931143835873"
          }
        },
        "ecfa648a-5738-4acd-a6f1-fe8b501e3873": {
          "type": "product",
          "settings": {
            "product": "meeting-booth-4-6-persons-old",
            "image": "shopify:\/\/shop_images\/XLarge_DarkGreen_DarkGreyInterior_None_03_e6aa5034-e022-4629-ad93-23ae7b606a48.png",
            "image_bg": "shopify:\/\/shop_images\/sbs-stn6-1-2-bg.jpg",
            "title": "Quell- Meeting Booth - 6 Person - No Furniture",
            "content": "<p>Tailor Your Workspace:<br\/>Choose Furniture or Create a Minimalist Setup<\/p><p> Flexibility is key to a<br\/>dynamic workspace. Our Quell 6-person meeting pod offers you the choice to<br\/>select your preferred furniture setup or create a minimalist environment. We<br\/>cater to your unique workspace requirements.<\/p>",
            "url": "\/products\/meeting-booth-4-6-persons?variant=42931143803105"
          }
        }
      },
      "block_order": [
        "ecfa648a-5738-4acd-a6f1-fe8b501e3872",
        "ecfa648a-5738-4acd-a6f1-fe8b501e3873"
      ],
      "custom_css": [
        ".index-section {padding: 0;}"
      ],
      "settings": {
        "collection": ""
      }
    },
    "c63be8cf-b0a5-4ef2-86c4-013e4d521eb1": {
      "type": "main-collection-next",
      "blocks": {
        "template--16816299114721__c63be8cf-b0a5-4ef2-86c4-013e4d521eb1-product-1": {
          "type": "product",
          "disabled": true,
          "settings": {
            "product": "soundproof-phone-booth",
            "image_bg": "shopify:\/\/shop_images\/sbs-stn6-1-2-bg.jpg",
            "title": "{{ block.settings.product.title }}",
            "content": "<p>In today's fast-paced and bustling work environment, it's no secret that busy environments can be chaotic, interruptive and frustrating.<\/p>",
            "url": "shopify:\/\/products\/soundproof-phone-booth"
          }
        },
        "template--16816299114721__c63be8cf-b0a5-4ef2-86c4-013e4d521eb1-product-2": {
          "type": "product",
          "disabled": true,
          "settings": {
            "product": "soundproof-phone-booth",
            "image": "shopify:\/\/shop_images\/Folio_Bar_Fly_Blush_01.png",
            "image_bg": "shopify:\/\/shop_images\/sbs-stn6-1-2-bg.jpg",
            "title": "{{ block.settings.product.title }}",
            "content": "<p>In today's fast-paced and bustling work environment, it's no secret that busy environments can be chaotic, interruptive and frustrating.<\/p>",
            "url": ""
          }
        },
        "28cea507-6689-4704-af63-50ae541df227": {
          "type": "email",
          "settings": {
            "title": "Thinking Outside The box, Inside The Booth....",
            "text": "<p>Stay Updated with Our Latest Innovations<\/p><p> Stay in the know about our latest events, product launches, upgrades, and more! Subscribe to our newsletter and be the first to explore innovations that enhance your workspace.<\/p>",
            "image_bg": "shopify:\/\/shop_images\/sbs-stn6-1-2-bg.jpg"
          }
        },
        "785f0f73-a5dd-4535-a55c-41ab723a40dc": {
          "type": "instagram",
          "settings": {
            "title": "Follow Us",
            "text": "<p><a href=\"https:\/\/www.instagram.com\/soundboxstore\/\" target=\"_blank\">@soundboxstore<\/a><\/p>",
            "image_bg": "shopify:\/\/shop_images\/sbs-stn6-3-4-bg.jpg"
          }
        },
        "314df900-6d6f-4125-aa7d-bd7ee3894428": {
          "type": "shopify:\/\/apps\/instafeed\/blocks\/app-block\/c447db20-095d-4a10-9725-b5977662c9d5",
          "disabled": true,
          "settings": {
            "html_area": "<div id=\"feed-24765\" class=\"instafeed-shopify\"><\/div>"
          }
        }
      },
      "block_order": [
        "template--16816299114721__c63be8cf-b0a5-4ef2-86c4-013e4d521eb1-product-1",
        "template--16816299114721__c63be8cf-b0a5-4ef2-86c4-013e4d521eb1-product-2",
        "28cea507-6689-4704-af63-50ae541df227",
        "785f0f73-a5dd-4535-a55c-41ab723a40dc",
        "314df900-6d6f-4125-aa7d-bd7ee3894428"
      ],
      "custom_css": [
        ".main-collection-next {padding: 10;}",
        ".collection-template-grid {padding: 10; gap: 10;}"
      ],
      "settings": {
        "collection": ""
      }
    },
    "main-collection-3": {
      "type": "main-collection-next",
      "blocks": {
        "ecfa648a-5738-4acd-a6f1-fe8b501e3872": {
          "type": "product",
          "settings": {
            "product": "meeting-booth-4-6-persons-old",
            "image": "shopify:\/\/shop_images\/4-6_Meeting_Pod_Charcoal_Wood_Set_02_02_3d6d5828-8586-40e3-ab87-1d2737d216f7.png",
            "image_bg": "shopify:\/\/shop_images\/sbs-stn6-3-4-bg.jpg",
            "title": "{{ block.settings.product.title }} - With Furniture",
            "content": "<p>Our latest product innovation: The all-in-one solution to combat noisy office environments - the acoustic phone booth paired with our cutting-edge electric adjustable desk.<\/p>",
            "url": "\/products\/meeting-booth-4-6-persons?variant=43641760612577"
          }
        },
        "ecfa648a-5738-4acd-a6f1-fe8b501e3873": {
          "type": "product",
          "settings": {
            "product": "meeting-booth-4-6-persons-old",
            "image": "shopify:\/\/shop_images\/XLarge_White_DarkGreyInterior_Set1_02_463db8d9-9fee-4bde-b845-4fa3b14aafca.png",
            "image_bg": "shopify:\/\/shop_images\/sbs-stn6-1-2-bg.jpg",
            "title": "{{ block.settings.product.title }} - No Furniture",
            "content": "<p>No matter your office aesthetics, our Quell Flex Stand Up will blend in effortlessly, enhancing the overall appeal of your workspace. Quick privacy call - No Problem!<\/p>",
            "url": "\/products\/meeting-booth-4-6-persons?variant=42931143835873"
          }
        }
      },
      "block_order": [
        "ecfa648a-5738-4acd-a6f1-fe8b501e3872",
        "ecfa648a-5738-4acd-a6f1-fe8b501e3873"
      ],
      "settings": {
        "collection": ""
      }
    },
    "5c80aa2e-8986-401d-b302-b4b94beb7891": {
      "type": "slideshow",
      "blocks": {
        "8190e8a1-3392-47ea-8fa7-dc5481d20bc6": {
          "type": "hero",
          "settings": {
            "top_subheading": "",
            "title": "<h2>Why Choose Our 6 Person Meeting Pod?<\/h2>",
            "title_size": 57,
            "subheading": "Expansive Design Accommodate larger teams comfortably with ample space for productive discussions.Exceptional AcousticsEnjoy top-tiersoundproofing for confidential meetings and presentations. Furniture Options Customise your pod's interior with the furniture setup that suits your needs.Versatile UseIdeal for team meetings,collaborative projects, and creative brainstorming sessions.",
            "link": "https:\/\/soundboxstore.com\/products\/soundproof-meeting-booth-3-4-persons",
            "link_text": "",
            "link_2": "",
            "link_text_2": "",
            "color_accent": "#ffffff",
            "text_align": "vertical-center horizontal-left",
            "image": "shopify:\/\/shop_images\/Xlrg_White-Banner-main-2.png",
            "image_mobile": "shopify:\/\/shop_images\/Xlrg_White-Banner-main-2-mob.png",
            "overlay_opacity": 20,
            "focal_point": "center center"
          }
        }
      },
      "block_order": [
        "8190e8a1-3392-47ea-8fa7-dc5481d20bc6"
      ],
      "custom_css": [
        ".index-section {padding: 0; margin: 0;}"
      ],
      "settings": {
        "full_width": true,
        "desktop_size": 0,
        "mobile_size": 0,
        "style": "minimal",
        "arrow_slide": false,
        "autoplay": false,
        "autoplay_speed": 5,
        "section_class": ""
      }
    },
    "main-collection-2": {
      "type": "main-collection-next",
      "blocks": {
        "ecfa648a-5738-4acd-a6f1-fe8b501e3872": {
          "type": "product",
          "settings": {
            "product": "office-phone-booth",
            "image": "shopify:\/\/shop_images\/Single_White_DarkGreyInterior_Set1_01_42076dd2-4e1d-4b98-966d-7b848deade84.png",
            "image_bg": "shopify:\/\/shop_images\/sbs-stn6-1-2-bg.jpg",
            "title": "{{ block.settings.product.title }} - With Furniture",
            "content": "<p>Looking for a solution to noisy office environments? Look no further than our top of the line acoustic controlled phone pods..<\/p>",
            "url": "shopify:\/\/products\/office-phone-booth"
          }
        },
        "ecfa648a-5738-4acd-a6f1-fe8b501e3873": {
          "type": "product",
          "settings": {
            "product": "office-phone-booth",
            "image": "shopify:\/\/shop_images\/Quell_Flex_No_Furniture_01_-_Dark_Green.png",
            "image_bg": "shopify:\/\/shop_images\/sbs-stn6-3-4-bg.jpg",
            "title": "{{ block.settings.product.title }} - No Furniture",
            "content": "<p>Our acoustic phone pods are designed to provide a private space for personal or private commercial conversations..<\/p>",
            "url": "https:\/\/soundboxstore.com\/products\/office-phone-booth?variant=42866925535457"
          }
        }
      },
      "block_order": [
        "ecfa648a-5738-4acd-a6f1-fe8b501e3872",
        "ecfa648a-5738-4acd-a6f1-fe8b501e3873"
      ],
      "disabled": true,
      "settings": {
        "collection": ""
      }
    },
    "77a1042c-44e2-40ba-adcb-f33ca7c5f3a5": {
      "type": "slideshow",
      "blocks": {
        "c5c3b471-2901-4491-b8c1-601483409611": {
          "type": "hero",
          "settings": {
            "top_subheading": "",
            "title": "<h1><strong>Blend & Mix<\/strong><\/h1>",
            "title_size": 57,
            "subheading": "Perfect mixing of booths and pods creates wellness, creative and morale!",
            "link": "",
            "link_text": "",
            "link_2": "",
            "link_text_2": "",
            "color_accent": "#ffffff",
            "text_align": "vertical-center horizontal-left",
            "image": "shopify:\/\/shop_images\/Catergory-Page-Solo-Room.png",
            "image_mobile": "shopify:\/\/shop_images\/Catergory-Page-Solo-Room-Mob.png",
            "overlay_opacity": 40,
            "focal_point": "center center"
          }
        }
      },
      "block_order": [
        "c5c3b471-2901-4491-b8c1-601483409611"
      ],
      "disabled": true,
      "custom_css": [
        ".index-section {padding: 0; margin: 0;}"
      ],
      "settings": {
        "full_width": true,
        "desktop_size": 0,
        "mobile_size": 0,
        "style": "minimal",
        "arrow_slide": false,
        "autoplay": false,
        "autoplay_speed": 5,
        "section_class": ""
      }
    },
    "04e915ad-dc54-4882-8c19-69a67c786f0b": {
      "type": "rich-text",
      "blocks": {
        "template--16816299114721__04e915ad-dc54-4882-8c19-69a67c786f0b-heading-1": {
          "type": "heading",
          "settings": {
            "title": "Elevate Collaboration with Our 6 Person Meeting Pod"
          }
        },
        "template--16816299114721__04e915ad-dc54-4882-8c19-69a67c786f0b-text-1": {
          "type": "text",
          "settings": {
            "enlarge_text": true,
            "text": "<p>Soundbox Store is your premier supplier of cutting-edge<br\/>sound solutions and innovative acoustic meeting booths. We are dedicated to reshaping the<br\/>way you conduct meetings and collaborate within your workspace.<\/p><p>Our intelligently designed 6-person pods provide a<br\/>soundproof and private space for confidential meetings, brainstorming sessions,<br\/>and creative endeavors. With exceptional acoustic dampening, integrated<br\/>ventilation, and customisable options, our 6-person desk pod embodies modern<br\/>office design, ensuring an inspiring atmosphere in your workplace.<\/p><p><strong>What Sets Our 6 Person Desk Pod<br\/>Apart?<\/strong><\/p><p>At Sound Box Store, we understand the<br\/>importance of creating a peaceful, distraction-free workspace. Our acoustic 6 person<br\/>acoustic meeting booths provide an ideal solution for businesses aiming to<br\/>optimise their office environment, group conference calls, and meetings.<\/p><p>Quality and service are at the core of<br\/>everything we offer at Soundbox Store. Our factory meticulously selects the<br\/>best recyclable materials, ensuring they meet the highest performance and<br\/>durability standards. Our knowledgeable team is always available to<br\/>assist you in finding the perfect product that aligns with your specific<br\/>requirements.<\/p><p><strong>Why Opt for Our 6 Person Desk Pod<br\/><\/strong>Power and Connectivity<br\/>Equipped with power pints, USB and USB-C ports to support your device.<\/p><p><strong>Design & Freedom<br\/><\/strong>Tailor the interior to match your offices style and functionality.<\/p><p><strong>Enhance Productivity<br\/><\/strong>Foster teamwork and collaboration on a larger scale with this spacious pod.<\/p>"
          }
        }
      },
      "block_order": [
        "template--16816299114721__04e915ad-dc54-4882-8c19-69a67c786f0b-heading-1",
        "template--16816299114721__04e915ad-dc54-4882-8c19-69a67c786f0b-text-1"
      ],
      "settings": {
        "align_text": "center",
        "narrow_column": false,
        "color_scheme": "none",
        "divider": false
      }
    },
    "9b3f8f21-95ee-4331-a1eb-6df3746f9449": {
      "type": "faq",
      "blocks": {
        "384182ef-0772-42c3-be48-f16f826fa4a0": {
          "type": "question",
          "settings": {
            "title": "What are the dimensions of the Quell 6 Person Office Pod?",
            "text": "<p>The Quell 6 Person Office Pod is designed to provide ample space for collaborative meetings. Its interior dimensions measure: Height: 214cm, Width: 204cm, and Depth: 210cm. This ensures that your team has plenty of room to work comfortably.<\/p>"
          }
        },
        "template--16818216698081__9b3f8f21-95ee-4331-a1eb-6df3746f9449-question-2": {
          "type": "question",
          "settings": {
            "title": "Can I customise the interior ofthe 6 Person Desk Pod to match our office's style and functionality?",
            "text": "<p>Yes, you can! At Soundbox Store, we offer customisation<br\/>options that allow you to tailor the interior of your 6 Person Desk Pod to<br\/>match your office's unique style and functionality requirements. Whether you<br\/>prefer a traditional conference room setup or a more creative and open<br\/>workspace, we can accommodate your needs.<\/p>"
          }
        },
        "template--16818216698081__9b3f8f21-95ee-4331-a1eb-6df3746f9449-question-1": {
          "type": "question",
          "settings": {
            "title": "How long does assembly take?",
            "text": "<p>Soundbox Stores large 6 person meting \/ conference booth, come in a number of parts that are logical to assembly. We do however suggest using our qualified and insured installers. The installer will take up to 3 hours to install the 6 Person acoustic pod once fully unpacked.<\/p>"
          }
        },
        "73aa4999-6a1d-48cb-8d71-404272acec31": {
          "type": "question",
          "settings": {
            "title": "Is special electric power supply required.",
            "text": "<p>All of our booths are plug and play, meaning once built there is an insert for a 13amp cable on the side of the booth which approximately 2 metres long. This is the simply plugged into your normal power socket.<\/p><p>(UK, Euro, US supplied dependent on delivery address) <\/p>"
          }
        },
        "9db25c39-b697-42aa-a02f-444c6e897ebe": {
          "type": "question",
          "settings": {
            "title": "How does the acoustic performance of the 6 Person Meeting Pod compare to smaller pods?",
            "text": "<p>The acoustic performance of our 6 Person Meeting Pod is<br\/>exceptional, just like our smaller pods. It offers top-tier soundproofing to<br\/>ensure that confidential discussions and presentations remain private and<br\/>undisturbed. The larger size of this pod is designed to accommodate more team<br\/>members without compromising on acoustic quality, making it an ideal choice for<br\/>collaborative meetings on a larger scale.<\/p>"
          }
        }
      },
      "block_order": [
        "384182ef-0772-42c3-be48-f16f826fa4a0",
        "template--16818216698081__9b3f8f21-95ee-4331-a1eb-6df3746f9449-question-2",
        "template--16818216698081__9b3f8f21-95ee-4331-a1eb-6df3746f9449-question-1",
        "73aa4999-6a1d-48cb-8d71-404272acec31",
        "9db25c39-b697-42aa-a02f-444c6e897ebe"
      ],
      "settings": {
        "title": "FAQs"
      }
    }
  },
  "order": [
    "79e8d093-77c2-4588-8678-9f011397b349",
    "main-collection",
    "c63be8cf-b0a5-4ef2-86c4-013e4d521eb1",
    "main-collection-3",
    "5c80aa2e-8986-401d-b302-b4b94beb7891",
    "main-collection-2",
    "77a1042c-44e2-40ba-adcb-f33ca7c5f3a5",
    "04e915ad-dc54-4882-8c19-69a67c786f0b",
    "9b3f8f21-95ee-4331-a1eb-6df3746f9449"
  ]
}
